mcp_server_deepresearch/__init__.py
mcp_server_deepresearch/__main__.py
mcp_server_deepresearch/server.py
mcp_server_deepresearch_yixing1684-0.3.1.dist-info/METADATA
mcp_server_deepresearch_yixing1684-0.3.1.dist-info/WHEEL
mcp_server_deepresearch_yixing1684-0.3.1.dist-info/entry_points.txt
mcp_server_deepresearch_yixing1684-0.3.1.dist-info/top_level.txt
mcp_server_deepresearch_yixing1684-0.3.1.dist-info/RECORD
