Metadata-Version: 2.4
Name: mcp-server-deepresearch-yixing1684
Version: 0.3.1
Summary: My trial project for MCP deployment
Requires-Python: >=3.12
Requires-Dist: mcp>=1.12.2
Requires-Dist: openai>=1.97.1
Requires-Dist: openai-agents>=0.2.4
Requires-Dist: pydantic>=2.11.7
